{
  "id": 34,
  "date": "2021-04-22T17:48:27+00:00",
  "subject": "Ny förfrågan: PHP Developer",
  "from": "Marcus Holm <marcus.holm@techlink.se>",
  "to": "inbox@dummy.se",
  "cc": "",
  "body": "Hej,\n\nNytt uppdrag som kan vara av intresse:\n\nKund: MediLink (healthcare)\nRoll: PHP Developer (senior)\nStart: ASAP\nLängd: 18 månader\nPlats: Stockholm / på plats\nArvode: 900 kr/h\n\nTeknikkrav:\n• PHP\n• GCP\n• Oracle\n\nKontakta mig om ni är intresserade!\n\nMvh,\nMarcus Holm, TechLink Sweden\n+46 70 234 56 78"
}