{
  "id": 146,
  "date": "2024-04-21T15:32:48+00:00",
  "subject": "New Opening: PHP Developer",
  "from": "Marcus Holm <marcus.holm@techlink.se>",
  "to": "inbox@dummy.se",
  "cc": "",
  "body": "Hi,\n\nHope you're having a good day! I'm reaching out about a new request from one of our clients.\n\nNordKart (e-commerce) is looking for a senior PHP Developer for a contract assignment.\n\nAssignment details:\n• Start: ASAP\n• Duration: 6 months\n• Location: Göteborg (hybrid)\n• Rate: up to 1050 SEK/h\n\nRequired tech:\n• PHP\n• GCP\n• RabbitMQ\n\nFeel free to reach out if you or someone in your network might be a good match!\n\nBest regards,\nMarcus Holm\nIT Recruitment Specialist\nTechLink Sweden\nTel: +46 70 234 56 78"
}