{
  "id": 174,
  "date": "2025-03-23T13:32:45+00:00",
  "subject": "New Request: Platform Engineer – Gaming",
  "from": "Anna Berg <anna.berg@nordstaff.se>",
  "to": "inbox@dummy.se",
  "cc": "",
  "body": "Hi,\n\nI'm writing to share a new consultant request that has just come in.\n\nCLIENT: NordPlay\nROLE: Junior Platform Engineer\nSTART: ASAP\nDURATION: 12 months\nLOCATION: Stockholm / hybrid\nRATE: 675 SEK/h\n\nThe team works primarily with Go, AWS, Docker, Redis and RabbitMQ.\n\nKey requirements:\n• Go\n• AWS\n• Docker\n• Redis\n• RabbitMQ\n\nDon't hesitate to reach out with any questions.\n\nBest regards,\nAnna Berg\nSenior Recruitment Consultant\nNordStaff AB\nTel: +46 72 123 45 67"
}